README.md
__init__.py
setup.py
gcdistance/__init__.py
gcdistance/gcdistance.py
gcdistance.egg-info/PKG-INFO
gcdistance.egg-info/SOURCES.txt
gcdistance.egg-info/dependency_links.txt
gcdistance.egg-info/requires.txt
gcdistance.egg-info/top_level.txt