Metadata-Version: 1.1
Name: gcdistance
Version: 0.0.1
Summary: This is an Example Package to calculate distances between points in a sphere with settable radius
Home-page: UNKNOWN
Author: Philipe Leal
Author-email: leal.philipe@gmail.com
License: UNKNOWN
Keywords: sphere two point distances
Platform: UNKNOWN
Classifier: License :: OSI Approved :: Python Software Foundation License
